{"preventUpnDetectSso":false,"silentUpdateTriggered":false,"featureLaunchInfo":{"enableUpnSilentSignin":-1},"previousCrashesInfo":{"crashes":[]},"windowState":{"monitorId":2763814474357314,"x":960,"y":0,"width":960,"height":1053,"isMaximized":false,"isFullScreen":false},"surfaceHubWindowState":{"monitorId":-1,"x":0,"y":0,"width":400,"height":600,"isMaximized":true,"isFullScreen":false},"restartCommand":{},"upnWindowUserUpn":"anubiz512z_gmail.com#EXT#@teamsclioutlookcom.onmicrosoft.com","userUpn":"","userOid":"08d3d890-22e8-4036-828b-15dab2a0990e","userTid":"c9fa8756-bafa-47d4-9d21-71f2b67c5e1f","guestTenantId":"","homeTenantId":"","webAccountId":"","webAccountProviderType":"","launchTime":"1634566674720","desktopZoomLevelV2":3,"guestTenantIds":{},"userAccounts":{},"signedInActiveUser":{},"tidOidMap":{},"isAppFirstRun":false,"upnScreenShowCount":0,"desktopSessionId":"desktop-e8b96a6d-a8b9-48ef-9798-8b83027c6cb0","teamsUrlProtocolsRegistered":false,"lyncUrlProtocolsRegistered":false,"disableWarningOnOpenKeyRegistered":false,"previousElectronVersion":"10.4.5","lastKnownElectronVersion":"10.4.5","signInRestrictionsLicenseType":"Free","machineId":"6d53294ce5c3f4fa839b4db3ec6693bf3c6e4ad797ca65fe8c7d82f18de57361","deviceInfoId":"a64b8f8de2bb6ef85503f0e70f2e6353aef32a81b733eaa297bb813b6b529aca","appPreferenceSettings":{"openAtLogin":false,"runningOnClose":true,"disableGpu":false,"enableMediaLoggingPreferenceKey":true},"currentWebLanguage":"en-GB","isForeground":true,"previousWebClientVersion":"41/1.0.0.2021101136","isLoggedOut":false,"theme":"darkV2","rendererCrashInfo":null,"isAppTerminated":false,"restartInfo":null,"notificationWindowOnClose":true}